crawlera_session/__init__.py
crawlera_session-1.2.8.dist-info/LICENSE
crawlera_session-1.2.8.dist-info/METADATA
crawlera_session-1.2.8.dist-info/WHEEL
crawlera_session-1.2.8.dist-info/top_level.txt
crawlera_session-1.2.8.dist-info/RECORD
