Metadata-Version: 2.1
Name: crawlera-session
Version: 1.2.8
Summary: Class that provides decorators and functions for easy handling of crawlera sessions in a scrapy spider.
Home-page: https://github.com/kalessin/crawlera-sessions
Author: Martin Olveyra
Author-email: molveyra@gmail.com
License: BSD
Classifier: Development Status :: 5 - Production/Stable
Classifier: Intended Audience :: Developers
Classifier: License :: OSI Approved :: BSD License
Classifier: Operating System :: OS Independent
Classifier: Programming Language :: Python :: 3
License-File: LICENSE
